LICENSE
README.md
setup.py
MeterSphere2Case/__init__.py
MeterSphere2Case/cli.py
MeterSphere2Case/compat.py
MeterSphere2Case/core.py
MeterSphere2Case/parser.py
ms2case.egg-info/PKG-INFO
ms2case.egg-info/SOURCES.txt
ms2case.egg-info/dependency_links.txt
ms2case.egg-info/entry_points.txt
ms2case.egg-info/top_level.txt