Metadata-Version: 2.1
Name: ms2case
Version: 0.0.7
Summary: Convert MeterSphere data to JSON testcases for HttpRunner.
Home-page: https://github.com/BSTester/MeterSphere2Case
Author: BSTester
Author-email: forpeng@foxmail.com
License: MIT
Keywords: MeterSphere converter json
Platform: UNKNOWN
Classifier: Development Status :: 3 - Alpha
Classifier: Programming Language :: Python :: 3.5
Classifier: Programming Language :: Python :: 3.6
Classifier: Programming Language :: Python :: 3.7
Classifier: Programming Language :: Python :: 3.8
Classifier: Programming Language :: Python :: 3.9
